foo/__about__.py
foo/__init__.py
foo/__main__.py
foo/bar.py
a_python_package-0.0.9.dist-info/LICENSE
a_python_package-0.0.9.dist-info/METADATA
a_python_package-0.0.9.dist-info/WHEEL
a_python_package-0.0.9.dist-info/entry_points.txt
a_python_package-0.0.9.dist-info/top_level.txt
a_python_package-0.0.9.dist-info/RECORD
